[{"id": 1441116320355942411, "verified": false, "tweet_text": "@cristalrubi5 I am SO happy for you \ud83d\ude0d\ud83d\udc4f\ud83e\udd7a you deserve all the love my Mexi twin!!!", "tweet_lang": "en", "tweet_date": "2021-09-23T19:00:00Z", "mentions": ["cristalrubi5"], "tweet_emoticons": ["\ud83d\ude0d", "\ud83d\udc4f", "\ud83e\udd7a"], "country": "USA", "text_en": "I am SO happy for you you deserve all the love my Mexi twin!!!", "replied_to_tweet_id": 1441104701903147011, "replied_to_user_id": 1053246896, "reply_text": "I am SO happy for you you deserve all the love my Mexi twin!!!"}, {"id": 1441116320355868690, "verified": false, "tweet_text": "@libslayer1917 @BCryptofash Marx would not deny that his theories are also the product of Enlightenment modernity.", "tweet_lang": "en", "tweet_date": "2021-09-23T19:00:00Z", "mentions": ["libslayer1917", "BCryptofash"], "country": "USA", "text_en": "Marx would not deny that his theories are also the product of Enlightenment modernity.", "replied_to_tweet_id": 1441116078298386439, "replied_to_user_id": 1401237264680861697, "reply_text": "Marx would not deny that his theories are also the product of Enlightenment modernity."}, {"id": 1441116320343343109, "verified": false, "tweet_text": "@momo_id7 good \ud83d\udc95\ud83d\ude44 u scared me tf", "tweet_lang": "en", "tweet_date": "2021-09-23T19:00:00Z", "mentions": ["momo_id7"], "tweet_emoticons": ["\ud83d\udc95", "\ud83d\ude44"], "country": "USA", "text_en": "good u scared me tf", "replied_to_tweet_id": 1441116063282855938, "replied_to_user_id": 1406694940428623875, "reply_text": "good u scared me tf"}, {"id": 1441116320284614657, "verified": false, "tweet_text": "@ATLFalconsUK @EliManning @Giants We both have poor o lines! It will go either way, low scoring or high and I\u2019m going for the latter. Patrick Graham has to change the defensive scheme for us because it\u2019s not soft coverage", "tweet_lang": "en", "tweet_date": "2021-09-23T19:00:00Z", "mentions": ["ATLFalconsUK", "EliManning", "Giants"], "country": "USA", "text_en": "We both have poor o lines! It will go either way, low scoring or high and Im going for the latter. Patrick Graham has to change the defensive scheme for us because its not soft coverage", "replied_to_tweet_id": 1441114164869537799, "replied_to_user_id": 1257412821073174528, "reply_text": "We both have poor o lines! It will go either way, low scoring or high and Im going for the latter. Patrick Graham has to change the defensive scheme for us because its not soft coverage"}, {"id": 1441116320251015179, "verified": false, "tweet_text": "@LostAlone37 The best reason to not be on Twitter.", "tweet_lang": "en", "tweet_date": "2021-09-23T19:00:00Z", "mentions": ["LostAlone37"], "country": "USA", "text_en": "The best reason to not be on Twitter.", "replied_to_tweet_id": 1441099571614998542, "replied_to_user_id": 1391808771442331651, "reply_text": "The best reason to not be on Twitter."}, {"id": 1441116320225890310, "verified": false, "tweet_text": "@christine_p_33 Where is this installation? My dad was drafted into the Navy in 66-67. It took him decades to feel proud about his service. He was laid to rest at the Willamette National Cemetery with full military honors. \u2764", "tweet_lang": "en", "tweet_date": "2021-09-23T19:00:00Z", "mentions": ["christine_p_33"], "tweet_emoticons": ["\u2764"], "country": "USA", "text_en": "Where is this installation? My dad was drafted into the Navy in -67. It took him decades to feel proud about his service. He was laid to rest at the Willamette National Cemetery with full military honors.", "replied_to_tweet_id": 1441109855087972356, "replied_to_user_id": 824419967185543168, "reply_text": "Where is this installation? My dad was drafted into the Navy in -67. It took him decades to feel proud about his service. He was laid to rest at the Willamette National Cemetery with full military honors."}, {}, {"id": 1441116320120987650, "verified": false, "tweet_text": "@UnathiNgwenya6 Mina I don\u2019t even know the person they\u2019re talking about Abeg Yoh", "tweet_lang": "en", "tweet_date": "2021-09-23T19:00:00Z", "mentions": ["UnathiNgwenya6"], "country": "USA", "text_en": "Mina I dont even know the person theyre talking about Abeg Yoh", "replied_to_tweet_id": 1441116086506700804, "replied_to_user_id": 1222193971373518849, "reply_text": "Mina I dont even know the person theyre talking about Abeg Yoh"}, {"id": 1441116320104210441, "verified": false, "tweet_text": "Now she\u2019s saying she doesn\u2019t have the money to pay for it\u2026.. send it back then, wtf. This was not free!??", "tweet_lang": "en", "tweet_date": "2021-09-23T19:00:00Z", "country": "USA", "text_en": "Now shes saying she doesnt have the money to pay for it.. send it back then, wtf. This was not free!??", "replied_to_tweet_id": 1441107196268318729, "replied_to_user_id": 519103031, "reply_text": "Now shes saying she doesnt have the money to pay for it.. send it back then, wtf. This was not free!??"}]