[{"id": 1441117116959100933, "verified": false, "tweet_text": "@ParanoidLinkie $LINKUSDT $LINK #CHAINLINK https://t.co/hQk9eiIEsV\n\nApollo 11 is preparing to launch CHAINLINK.\nTarget: the sky.  \n\nLFG.", "tweet_lang": "en", "tweet_date": "2021-09-23T19:00:00Z", "hashtags": ["CHAINLINK"], "mentions": ["ParanoidLinkie"], "tweet_urls": ["https://t.co/hQk9eiIEsV"], "country": "USA", "text_en": "$LINKUSDT $LINK Apollo is preparing to launch CHAINLINK. Target: the sky. LFG.", "replied_to_tweet_id": 1440986634774790145, "replied_to_user_id": 2995363010, "reply_text": "$LINKUSDT $LINK Apollo is preparing to launch CHAINLINK. Target: the sky. LFG."}, {"id": 1441117116942274573, "verified": false, "tweet_text": "@duckygyu i\u2019m literally the same person as soobin it\u2019s scary", "tweet_lang": "en", "tweet_date": "2021-09-23T19:00:00Z", "mentions": ["duckygyu"], "country": "USA", "text_en": "im literally the same person as soobin its scary", "replied_to_tweet_id": 1441116603316256778, "replied_to_user_id": 1401275204375044103, "reply_text": "im literally the same person as soobin its scary"}, {"id": 1441117116900405253, "verified": false, "tweet_text": "@crademacher2006 @jb_props Looking at workload last week I agree Latavius is getting looks.  Freeman is not anything to worry about.  I watched him with Giants last year.  His productive days are done.  Bell could mess things up though. I think the team loves Ty\u2019son.", "tweet_lang": "en", "tweet_date": "2021-09-23T19:00:00Z", "mentions": ["crademacher2006", "jb_props"], "country": "USA", "text_en": "Looking at workload last week I agree Latavius is getting looks. Freeman is not anything to worry about. I watched him with Giants last year. His productive days are done. Bell could mess things up though. I think the team loves Tyson.", "replied_to_tweet_id": 1441092339867406352, "replied_to_user_id": 3171125472, "reply_text": "Looking at workload last week I agree Latavius is getting looks. Freeman is not anything to worry about. I watched him with Giants last year. His productive days are done. Bell could mess things up though. I think the team loves Tyson."}, {"id": 1441117116892024833, "verified": false, "tweet_text": "@Demonic_pk @AdamGrenade That\u2019s not the point. Besides, he doesn\u2019t just posted straight gameplay.", "tweet_lang": "en", "tweet_date": "2021-09-23T19:00:00Z", "mentions": ["Demonic_pk", "AdamGrenade"], "country": "USA", "text_en": "Thats not the point. Besides, he doesnt just posted straight gameplay.", "replied_to_tweet_id": 1441107799740538882, "replied_to_user_id": 1337115759185686530, "reply_text": "Thats not the point. Besides, he doesnt just posted straight gameplay."}, {"id": 1441117116791341062, "verified": false, "tweet_text": "@dstrtnz But that's like 1/4 on the bri'ain meter", "tweet_lang": "en", "tweet_date": "2021-09-23T19:00:00Z", "mentions": ["dstrtnz"], "country": "USA", "text_en": "But that's like /4 on the bri'ain meter", "replied_to_tweet_id": 1441114572564275211, "replied_to_user_id": 986249960504119297, "reply_text": "But that's like /4 on the bri'ain meter"}, {"id": 1441117116753596427, "verified": false, "tweet_text": "@JustinW09252026 @dustybizzle @missmarsii @ChrisAlbertoLaw @Fatueze Do I have the freedom to drive 100 mph outside your home?  If you are afraid, you can always stay home.  Whenever it threatens public good, there are limitations to our choices.", "tweet_lang": "en", "tweet_date": "2021-09-23T19:00:00Z", "mentions": ["JustinW09252026", "dustybizzle", "missmarsii", "ChrisAlbertoLaw", "Fatueze"], "country": "USA", "text_en": "Do I have the freedom to drive mph outside your home? If you are afraid, you can always stay home. Whenever it threatens public good, there are limitations to our choices.", "replied_to_tweet_id": 1441097026918252554, "replied_to_user_id": 1389048095435014157, "reply_text": "Do I have the freedom to drive mph outside your home? If you are afraid, you can always stay home. Whenever it threatens public good, there are limitations to our choices."}, {"id": 1441117116749340672, "verified": false, "tweet_text": "@tcburkejr My dream tbh.", "tweet_lang": "en", "tweet_date": "2021-09-23T19:00:00Z", "mentions": ["tcburkejr"], "country": "USA", "text_en": "My dream tbh.", "replied_to_tweet_id": 1441116927867310084, "replied_to_user_id": 239950574, "reply_text": "My dream tbh."}, {"id": 1441117116741021699, "verified": false, "tweet_text": "@bme_777 Mine too, right there in the middle \ud83c\udf1a", "tweet_lang": "en", "tweet_date": "2021-09-23T19:00:00Z", "mentions": ["bme_777"], "tweet_emoticons": ["\ud83c\udf1a"], "country": "USA", "text_en": "Mine too, right there in the middle", "replied_to_tweet_id": 1440982968525275139, "replied_to_user_id": 1006278362384556039, "reply_text": "Mine too, right there in the middle"}]