[{"id": 1441116279075528709, "verified": false, "tweet_text": "@P2WFantasy @CharlesChillFFB Asking the important questions.", "tweet_lang": "en", "tweet_date": "2021-09-23T19:00:00Z", "mentions": ["P2WFantasy", "CharlesChillFFB"], "country": "USA", "text_en": "Asking the important questions.", "replied_to_tweet_id": 1441116166366195715, "replied_to_user_id": 1242458427814825996, "reply_text": "Asking the important questions."}, {"id": 1441116279021072395, "verified": false, "tweet_text": "@TheDimpledRN @ShellPatreaux Awww thank you so much for the kind words \ud83d\udc9c\ud83d\udc9c yes I do.", "tweet_lang": "en", "tweet_date": "2021-09-23T19:00:00Z", "mentions": ["TheDimpledRN", "ShellPatreaux"], "tweet_emoticons": ["\ud83d\udc9c"], "country": "USA", "text_en": "Awww thank you so much for the kind words yes I do.", "replied_to_tweet_id": 1441115997419704324, "replied_to_user_id": 36508550, "reply_text": "Awww thank you so much for the kind words yes I do."}, {"id": 1441116278937178114, "verified": false, "tweet_text": "@marzipaninis It\u2019s good", "tweet_lang": "en", "tweet_date": "2021-09-23T19:00:00Z", "mentions": ["marzipaninis"], "country": "USA", "text_en": "Its good", "replied_to_tweet_id": 1441115603507421187, "replied_to_user_id": 713217464, "reply_text": "Its good"}, {"id": 1441116278932979715, "verified": false, "tweet_text": "@KayKimXVII I couldn\u2019t bring myself to change it I love ha sm but she crossed the line it\u2019s done \ud83d\ude35\u200d\ud83d\udcab", "tweet_lang": "en", "tweet_date": "2021-09-23T19:00:00Z", "mentions": ["KayKimXVII"], "tweet_emoticons": ["\ud83d\ude35\u200d\ud83d\udcab"], "country": "USA", "text_en": "I couldnt bring myself to change it I love ha sm but she crossed the line its done", "replied_to_tweet_id": 1441115750438092802, "replied_to_user_id": 788046481, "reply_text": "I couldnt bring myself to change it I love ha sm but she crossed the line its done"}, {"id": 1441116278907817985, "verified": false, "tweet_text": "@AlgoDicks @EFoxAJ dicks are the new faces", "tweet_lang": "en", "tweet_date": "2021-09-23T19:00:00Z", "mentions": ["AlgoDicks", "EFoxAJ"], "country": "USA", "text_en": "dicks are the new faces", "replied_to_tweet_id": 1441112307115823113, "replied_to_user_id": 1435014780754927617, "reply_text": "dicks are the new faces"}, {"id": 1441116278907760650, "verified": false, "tweet_text": "@sarahhazel15 @grahamandre @aly_sea @wendystewart78 @Annie_McS @9teaNinePercent @TriciaPower1 @CreativityMrs @rondelle10_b @MrEFinch It looks dated....I loved it at the time.", "tweet_lang": "en", "tweet_date": "2021-09-23T19:00:00Z", "mentions": ["sarahhazel15", "grahamandre", "aly_sea", "wendystewart78", "Annie_McS", "9teaNinePercent", "TriciaPower1", "CreativityMrs", "rondelle10_b", "MrEFinch"], "country": "USA", "text_en": "It looks dated....I loved it at the time.", "replied_to_tweet_id": 1441115999420370954, "replied_to_user_id": 712660655657132034, "reply_text": "It looks dated....I loved it at the time."}, {"id": 1441116278878474250, "verified": false, "tweet_text": "https://t.co/E49LbR5Rl8 https://t.co/uhKcjHnKll Rump\u2019s attorneys never once claimed \"fraud\" in court - - only in front of TV.", "tweet_lang": "en", "tweet_date": "2021-09-23T19:00:00Z", "tweet_urls": ["https://t.co/E49LbR5Rl8", "https://t.co/uhKcjHnKll"], "country": "USA", "text_en": "Rumps attorneys never once claimed \"fraud\" in court - - only in front of TV.", "replied_to_tweet_id": 1441115299055427590, "replied_to_user_id": 247642500, "reply_text": "Rumps attorneys never once claimed \"fraud\" in court - - only in front of TV."}, {"id": 1441116278844837888, "verified": false, "tweet_text": "@CBS4Mark @KarenMorfitt @CBSDenver @DowntownDenver @DenBicycleLobby Honesty I prefer they spent the money to help the homeless folks downtown. But hey, we always need another bike trail right?", "tweet_lang": "en", "tweet_date": "2021-09-23T19:00:00Z", "mentions": ["CBS4Mark", "KarenMorfitt", "CBSDenver", "DowntownDenver", "DenBicycleLobby"], "country": "USA", "text_en": "Honesty I prefer they spent the money to help the homeless folks downtown. But hey, we always need another bike trail right?", "replied_to_tweet_id": 1440877630358761472, "replied_to_user_id": 529555640, "reply_text": "Honesty I prefer they spent the money to help the homeless folks downtown. But hey, we always need another bike trail right?"}, {"id": 1441116278828142604, "verified": false, "tweet_text": "@nanaYhawforina He dey everywhere charlie. He go dey the DM our attack go be better pass", "tweet_lang": "en", "tweet_date": "2021-09-23T19:00:00Z", "mentions": ["nanaYhawforina"], "country": "USA", "text_en": "He dey everywhere charlie. He go dey the DM our attack go be better pass", "replied_to_tweet_id": 1441115893992288264, "replied_to_user_id": 949915507985125376, "reply_text": "He dey everywhere charlie. He go dey the DM our attack go be better pass"}]