[{"id": 1441116768701849604, "verified": false, "tweet_text": "@Xated_Morenike okay! they should\u2019ve led with the mess and i may have been more intrigued. \ud83d\ude2d", "tweet_lang": "en", "tweet_date": "2021-09-23T19:00:00Z", "mentions": ["Xated_Morenike"], "tweet_emoticons": ["\ud83d\ude2d"], "country": "USA", "text_en": "okay! they shouldve led with the mess and i may have been more intrigued.", "replied_to_tweet_id": 1441114471821295623, "replied_to_user_id": 824828632443060225, "reply_text": "okay! they shouldve led with the mess and i may have been more intrigued."}, {"id": 1441116768697667584, "verified": false, "tweet_text": "@traderrocko $LINKUSDT $LINK #CHAINLINK https://t.co/hQk9eiIEsV\n\nApollo 11 is preparing to launch CHAINLINK.\nTarget: the sky.  \n\nLFG.", "tweet_lang": "en", "tweet_date": "2021-09-23T19:00:00Z", "hashtags": ["CHAINLINK"], "mentions": ["traderrocko"], "tweet_urls": ["https://t.co/hQk9eiIEsV"], "country": "USA", "text_en": "$LINKUSDT $LINK Apollo is preparing to launch CHAINLINK. Target: the sky. LFG.", "replied_to_tweet_id": 1441002619191926786, "replied_to_user_id": 955920554325872640, "reply_text": "$LINKUSDT $LINK Apollo is preparing to launch CHAINLINK. Target: the sky. LFG."}, {"id": 1441116768693456902, "verified": false, "tweet_text": "@Baby_Lovely_Inu Good project", "tweet_lang": "en", "tweet_date": "2021-09-23T19:00:00Z", "mentions": ["Baby_Lovely_Inu"], "country": "USA", "text_en": "Good project", "replied_to_tweet_id": 1440578471747469324, "replied_to_user_id": 1436408223053979649, "reply_text": "Good project"}, {"id": 1441116768664129544, "verified": false, "tweet_text": "@Pokemon Lol okay that was a good one, well done! https://t.co/gzBMK1tCbG", "tweet_lang": "en", "tweet_date": "2021-09-23T19:00:00Z", "mentions": ["Pokemon"], "country": "USA", "text_en": "Lol okay that was a good one, well done!", "replied_to_tweet_id": 1441115170491625483, "replied_to_user_id": 96879107, "reply_text": "Lol okay that was a good one, well done!"}, {"id": 1441116768638889987, "verified": false, "tweet_text": "@embuswell doing the lords work for me xxxxx", "tweet_lang": "en", "tweet_date": "2021-09-23T19:00:00Z", "mentions": ["embuswell"], "country": "USA", "text_en": "doing the lords work for me xxxxx", "replied_to_tweet_id": 1441116390421721092, "replied_to_user_id": 915982268275011587, "reply_text": "doing the lords work for me xxxxx"}, {"id": 1441116768525684736, "verified": false, "tweet_text": "@1znzkdz Take me back to the old days \n#AlpNavruz \n#Ay\u00e7aAy\u015finTuran \n#PoyHaz \n#AdaMasal\u0131", "tweet_lang": "en", "tweet_date": "2021-09-23T19:00:00Z", "hashtags": ["AlpNavruz", "Ay\u00e7aAy\u015finTuran", "PoyHaz", "AdaMasal\u0131"], "mentions": ["1znzkdz"], "country": "USA", "text_en": "Take me back to the old days", "replied_to_tweet_id": 1441111671020285968, "replied_to_user_id": 1181866012679049216, "reply_text": "Take me back to the old days"}, {"id": 1441116768521494529, "verified": false, "tweet_text": "@Raveniffaz I WILL GET THE iRA LEGGIIIIIIIES \u263a\ufe0f\u263a\ufe0f\ud83d\ude24\ud83d\ude24\u263a\ufe0f\ud83d\udc95\u263a\ufe0f\ud83d\udc95\ud83d\ude24\ud83d\udc95\ud83d\udc95\ud83d\udc95", "tweet_lang": "en", "tweet_date": "2021-09-23T19:00:00Z", "mentions": ["Raveniffaz"], "tweet_emoticons": ["\ud83d\udc95", "\ud83d\ude24", "\u263a\ufe0f"], "country": "USA", "text_en": "I WILL GET THE iRA LEGGIIIIIIIES", "replied_to_tweet_id": 1441114825422094346, "replied_to_user_id": 3892406540, "reply_text": "I WILL GET THE iRA LEGGIIIIIIIES"}, {"id": 1441116768496275456, "verified": false, "tweet_text": "@ErikJLarsen Genetically, we are a mile from humans at the time of Christ. If God is checking our DNA we are all fucked anyway. Thank your local retrovirus for that.", "tweet_lang": "en", "tweet_date": "2021-09-23T19:00:00Z", "mentions": ["ErikJLarsen"], "country": "USA", "text_en": "Genetically, we are a mile from humans at the time of Christ. If God is checking our DNA we are all fucked anyway. Thank your local retrovirus for that.", "replied_to_tweet_id": 1441076695818125313, "replied_to_user_id": 30891969, "reply_text": "Genetically, we are a mile from humans at the time of Christ. If God is checking our DNA we are all fucked anyway. Thank your local retrovirus for that."}, {"id": 1441116768462725128, "verified": false, "tweet_text": "@failedmanman I\u2019d take the quill and carve her face with it.", "tweet_lang": "en", "tweet_date": "2021-09-23T19:00:00Z", "mentions": ["failedmanman"], "country": "USA", "text_en": "Id take the quill and carve her face with it.", "replied_to_tweet_id": 1441116189015502850, "replied_to_user_id": 880435736482369537, "reply_text": "Id take the quill and carve her face with it."}, {"id": 1441116768399880193, "verified": false, "tweet_text": "@therecount The three branches of Government: The fourth Estate is Free Press- NoT a Bible.\n\nIn fact- separation of Church and State, No religious test/oath, Freedom of Religion are all part of our Founding.\n\nThe Christian Bible- or any other, isn\u2019t part of our Government.", "tweet_lang": "en", "tweet_date": "2021-09-23T19:00:00Z", "mentions": ["therecount"], "country": "USA", "text_en": "The three branches of Government: The fourth Estate is Free Press- NoT a Bible. In fact- separation of Church and State, No religious test/oath, Freedom of Religion are all part of our Founding. The Christian Bible- or any other, isnt part of our Government.", "replied_to_tweet_id": 1441003080296894467, "replied_to_user_id": 1087380412089987077, "reply_text": "The three branches of Government: The fourth Estate is Free Press- NoT a Bible. In fact- separation of Church and State, No religious test/oath, Freedom of Religion are all part of our Founding. The Christian Bible- or any other, isnt part of our Government."}]