[{"id": 1441117158977667078, "verified": false, "tweet_text": "@dudleylad1066 Mass TAKE THE PISS MIGRATION!", "tweet_lang": "en", "tweet_date": "2021-09-23T19:00:00Z", "mentions": ["dudleylad1066"], "country": "USA", "text_en": "Mass TAKE THE PISS MIGRATION!", "replied_to_tweet_id": 1441022179253145611, "replied_to_user_id": 4005111863, "reply_text": "Mass TAKE THE PISS MIGRATION!"}, {"id": 1441117158977638408, "verified": false, "tweet_text": "@DRAFZALNIAZ2 The reason of\u2019Plandemic\u2019.", "tweet_lang": "en", "tweet_date": "2021-09-23T19:00:00Z", "mentions": ["DRAFZALNIAZ2"], "country": "USA", "text_en": "The reason ofPlandemic.", "replied_to_tweet_id": 1441113670168158216, "replied_to_user_id": 1400833754072064002, "reply_text": "The reason ofPlandemic."}, {"id": 1441117158973394945, "verified": false, "tweet_text": "...Spoke too soon. That wasn't the Christmas ep. The real Xmas ep was still pretty bleak. Poor Susan. \ud83d\ude1e But at least Div didn't wander off into the streets, never to be seen again, like Alan Alda's character. As far as we know.\nAlso Doug is a jerk who looks good in a tux. #ER", "tweet_lang": "en", "tweet_date": "2021-09-23T19:00:00Z", "hashtags": ["ER"], "tweet_emoticons": ["\ud83d\ude1e"], "country": "USA", "text_en": "...Spoke too soon. That wasn't the Christmas ep. The real Xmas ep was still pretty bleak. Poor Susan. But at least Div didn't wander off into the streets, never to be seen again, like Alan Alda's character. As far as we know. Also Doug is a jerk who looks good in a tux.", "replied_to_tweet_id": 1440861903467606018, "replied_to_user_id": 208128958, "reply_text": "...Spoke too soon. That wasn't the Christmas ep. The real Xmas ep was still pretty bleak. Poor Susan. But at least Div didn't wander off into the streets, never to be seen again, like Alan Alda's character. As far as we know. Also Doug is a jerk who looks good in a tux."}, {"id": 1441117158918934534, "verified": false, "tweet_text": "@infosfcb @StormDesignzz Take the ball and cross the ball 2.0", "tweet_lang": "en", "tweet_date": "2021-09-23T19:00:00Z", "mentions": ["infosfcb", "StormDesignzz"], "country": "USA", "text_en": "Take the ball and cross the ball", "replied_to_tweet_id": 1441115004908937224, "replied_to_user_id": 4365185421, "reply_text": "Take the ball and cross the ball"}]