[{"id": 1441116646899290120, "verified": false, "tweet_text": "@J_Bertt11 @RavenSoftware @JoeCecot Only game out at the moment \ud83e\udd37\ud83c\udffc\u200d\u2642\ufe0f have to wait until December 8th for Halo but its a legit question seeing as when our characters put Armor plates on they put them into the chest of our vests", "tweet_lang": "en", "tweet_date": "2021-09-23T19:00:00Z", "mentions": ["J_Bertt11", "RavenSoftware", "JoeCecot"], "tweet_emoticons": ["\ud83e\udd37\ud83c\udffc\u200d\u2642\ufe0f"], "country": "USA", "text_en": "Only game out at the moment have to wait until December th for Halo but its a legit question seeing as when our characters put Armor plates on they put them into the chest of our vests", "replied_to_tweet_id": 1441115930759557131, "replied_to_user_id": 453471948, "reply_text": "Only game out at the moment have to wait until December th for Halo but its a legit question seeing as when our characters put Armor plates on they put them into the chest of our vests"}, {"id": 1441116646857330688, "verified": false, "tweet_text": "@ESPNNBA Game 7 OKC vs GSW, OKC wins and goes on to (maybe) win the title", "tweet_lang": "en", "tweet_date": "2021-09-23T19:00:00Z", "mentions": ["ESPNNBA"], "country": "USA", "text_en": "Game OKC vs GSW, OKC wins and goes on to (maybe) win the title", "replied_to_tweet_id": 1441026213628284929, "replied_to_user_id": 74518740, "reply_text": "Game OKC vs GSW, OKC wins and goes on to (maybe) win the title"}, {"id": 1441116646857314311, "verified": false, "tweet_text": "@ImSpeaking13 Kicking the can down the road..", "tweet_lang": "en", "tweet_date": "2021-09-23T19:00:00Z", "mentions": ["ImSpeaking13"], "country": "USA", "text_en": "Kicking the can down the road..", "replied_to_tweet_id": 1441065878427029507, "replied_to_user_id": 2640729706, "reply_text": "Kicking the can down the road.."}, {"id": 1441116646848880652, "verified": false, "tweet_text": "@RandPaul The infrastructure bill is paid for by taxes on the wealthy and large Corps. It does not add the deficit left by Republicans", "tweet_lang": "en", "tweet_date": "2021-09-23T19:00:00Z", "mentions": ["RandPaul"], "country": "USA", "text_en": "The infrastructure bill is paid for by taxes on the wealthy and large Corps. It does not add the deficit left by Republicans", "replied_to_tweet_id": 1441023913564192768, "replied_to_user_id": 216881337, "reply_text": "The infrastructure bill is paid for by taxes on the wealthy and large Corps. It does not add the deficit left by Republicans"}, {"id": 1441116646840492037, "verified": false, "tweet_text": "@FWBESS Im the choosen one", "tweet_lang": "en", "tweet_date": "2021-09-23T19:00:00Z", "mentions": ["FWBESS"], "country": "USA", "text_en": "Im the choosen one", "replied_to_tweet_id": 1441112634372210689, "replied_to_user_id": 1298908543618183169, "reply_text": "Im the choosen one"}, {"id": 1441116646756667402, "verified": false, "tweet_text": "@1lowmill Yes I'll be in the usual place, surrounded by sheep for two days. Hope to see you then", "tweet_lang": "en", "tweet_date": "2021-09-23T19:00:00Z", "mentions": ["1lowmill"], "country": "USA", "text_en": "Yes I'll be in the usual place, surrounded by sheep for two days. Hope to see you then", "replied_to_tweet_id": 1441116069456875524, "replied_to_user_id": 528684039, "reply_text": "Yes I'll be in the usual place, surrounded by sheep for two days. Hope to see you then"}, {}]