[{"id": 1441117008083361793, "verified": false, "tweet_text": "@MJ_Stables Wondering whether this could be a measurable thing to show on data sites like yours in the future \ni.e. how good the horse is at recovery.\n\nI guess it's hard to measure with fatigue only available to the stable owners.", "tweet_lang": "en", "tweet_date": "2021-09-23T19:00:00Z", "mentions": ["MJ_Stables"], "country": "USA", "text_en": "Wondering whether this could be a measurable thing to show on data sites like yours in the future i.e. how good the horse is at recovery. I guess it's hard to measure with fatigue only available to the stable owners.", "replied_to_tweet_id": 1441116149861679107, "replied_to_user_id": 1348301795064487940, "reply_text": "Wondering whether this could be a measurable thing to show on data sites like yours in the future i.e. how good the horse is at recovery. I guess it's hard to measure with fatigue only available to the stable owners."}, {"id": 1441117008079196169, "verified": false, "tweet_text": "@XpengGuru Love the P7 https://t.co/TivvBHYifZ", "tweet_lang": "en", "tweet_date": "2021-09-23T19:00:00Z", "mentions": ["XpengGuru"], "country": "USA", "text_en": "Love the P7", "replied_to_tweet_id": 1441111456792006671, "replied_to_user_id": 1340821595544317953, "reply_text": "Love the P7"}, {"id": 1441117008074993668, "verified": false, "tweet_text": "@yatogamisbitch i'll let linus do the drop https://t.co/pYIc7ZqirR", "tweet_lang": "en", "tweet_date": "2021-09-23T19:00:00Z", "mentions": ["yatogamisbitch"], "country": "USA", "text_en": "i'll let linus do the drop", "replied_to_tweet_id": 1441106544674758665, "replied_to_user_id": 1028032133678477313, "reply_text": "i'll let linus do the drop"}, {"id": 1441117008024649728, "verified": false, "tweet_text": "@endorphinique @caelyncobb Glad I wasn\u2019t the only one to take 1 of each!", "tweet_lang": "en", "tweet_date": "2021-09-23T19:00:00Z", "mentions": ["endorphinique", "caelyncobb"], "country": "USA", "text_en": "Glad I wasnt the only one to take of each!", "replied_to_tweet_id": 1441107890836688904, "replied_to_user_id": 531890549, "reply_text": "Glad I wasnt the only one to take of each!"}, {"id": 1441117007974318090, "verified": false, "tweet_text": "@TherealNihal Sold!", "tweet_lang": "en", "tweet_date": "2021-09-23T19:00:00Z", "mentions": ["TherealNihal"], "country": "USA", "text_en": "Sold!", "replied_to_tweet_id": 1441116511578439691, "replied_to_user_id": 19313770, "reply_text": "Sold!"}, {"id": 1441117007949094915, "verified": false, "tweet_text": "@1kimichan Jerlea rested his forehead on the door. \"Kimi...Honey. Open the door please.\" His voice was sill calming. \n\nHe'd wave his hand at the Sensi, he wanted her to be ready to talk not forced into it like most adults would do.", "tweet_lang": "en", "tweet_date": "2021-09-23T19:00:00Z", "mentions": ["1kimichan"], "country": "USA", "text_en": "Jerlea rested his forehead on the door. \"Kimi...Honey. Open the door please.\" His voice was sill calming. He'd wave his hand at the Sensi, he wanted her to be ready to talk not forced into it like most adults would do.", "replied_to_tweet_id": 1441116243675648000, "replied_to_user_id": 1086580767369715712, "reply_text": "Jerlea rested his forehead on the door. \"Kimi...Honey. Open the door please.\" His voice was sill calming. He'd wave his hand at the Sensi, he wanted her to be ready to talk not forced into it like most adults would do."}, {"id": 1441117007865270281, "verified": false, "tweet_text": "@taeminxgod THE COLORS ARE BEAUTIFUL TRULY \ud83d\ude2d\ud83d\ude2d", "tweet_lang": "en", "tweet_date": "2021-09-23T19:00:00Z", "mentions": ["taeminxgod"], "tweet_emoticons": ["\ud83d\ude2d"], "country": "USA", "text_en": "THE COLORS ARE BEAUTIFUL TRULY", "replied_to_tweet_id": 1441116875220393984, "replied_to_user_id": 1003071284551569408, "reply_text": "THE COLORS ARE BEAUTIFUL TRULY"}]