[{"id": 1441117584565293060, "verified": false, "tweet_text": "@weather_god @EvenRouault It's something that the spec leaves room for, but I can't seem to find examples of anyone using that particular bit of \"wiggle room\" in the spec...", "tweet_lang": "en", "tweet_date": "2021-09-23T19:00:00Z", "mentions": ["weather_god", "EvenRouault"], "country": "USA", "text_en": "It's something that the spec leaves room for, but I can't seem to find examples of anyone using that particular bit of \"wiggle room\" in the spec...", "replied_to_tweet_id": 1441117287344324616, "replied_to_user_id": 4711528158, "reply_text": "It's something that the spec leaves room for, but I can't seem to find examples of anyone using that particular bit of \"wiggle room\" in the spec..."}, {"id": 1441117584552693761, "verified": false, "tweet_text": "@PoliticsForAlI Good", "tweet_lang": "en", "tweet_date": "2021-09-23T19:00:00Z", "mentions": ["PoliticsForAlI"], "country": "USA", "text_en": "Good", "replied_to_tweet_id": 1441088468965232641, "replied_to_user_id": 1166419406685188101, "reply_text": "Good"}, {"id": 1441117584544305164, "verified": false, "tweet_text": "@W_F_Magee @SandyGonads33 still the greatest tweet of all time", "tweet_lang": "en", "tweet_date": "2021-09-23T19:00:00Z", "mentions": ["W_F_Magee", "SandyGonads33"], "country": "USA", "text_en": "still the greatest tweet of all time", "replied_to_tweet_id": 1393543841429565440, "replied_to_user_id": 1252691288, "reply_text": "still the greatest tweet of all time"}, {"id": 1441117584422699014, "verified": false, "tweet_text": "@_lqm2_ Tax the dead, literal haja", "tweet_lang": "es", "tweet_date": "2021-09-23T19:00:00Z", "mentions": ["_lqm2_"], "country": "MEXICO", "text_es": "Tax the dead, literal haja", "replied_to_tweet_id": 1441115680179306503, "replied_to_user_id": 491896220, "reply_text": "Tax the dead, literal haja"}, {"id": 1441117584389144587, "verified": false, "tweet_text": "@TheHalfVolley1 oh yes. also loved seeing it again in the S3 finale montage. Wish it made its way into the series finale montage, too", "tweet_lang": "en", "tweet_date": "2021-09-23T19:00:00Z", "mentions": ["TheHalfVolley1"], "country": "USA", "text_en": "oh yes. also loved seeing it again in the S3 finale montage. Wish it made its way into the series finale montage, too", "replied_to_tweet_id": 1441117347612299266, "replied_to_user_id": 88905915, "reply_text": "oh yes. also loved seeing it again in the S3 finale montage. Wish it made its way into the series finale montage, too"}]